LICENSE
MANIFEST.in
README.md
README.rst
setup.cfg
setup.py
django_last_active.egg-info/PKG-INFO
django_last_active.egg-info/SOURCES.txt
django_last_active.egg-info/dependency_links.txt
django_last_active.egg-info/requires.txt
django_last_active.egg-info/top_level.txt
last_active/__init__.py
last_active/admin.py
last_active/apps.py
last_active/middleware.py
last_active/models.py
last_active/settings.py
last_active/tests.py
last_active/views.py
last_active/migrations/0001_initial.py
last_active/migrations/__init__.py